LICENSE
gpg_keymanager/__init__.py
gpg_keymanager/bin/__init__.py
gpg_keymanager/bin/commands/__init__.py
gpg_keymanager/bin/commands/base.py
gpg_keymanager/bin/commands/list_public_keys.py
gpg_keymanager/bin/gpg_keymanager.py
gpg_keymanager/editor.py
gpg_keymanager/exceptions.py
gpg_keymanager/keys/__init__.py
gpg_keymanager/keys/base.py
gpg_keymanager/keys/constants.py
gpg_keymanager/keys/directory.py
gpg_keymanager/keys/parser.py
gpg_keymanager/keys/public_key.py
gpg_keymanager/keys/trustdb.py
gpg_keymanager/keys/utils.py
gpg_keymanager/platform/__init__.py
gpg_keymanager/store/__init__.py
gpg_keymanager/store/constants.py
gpg_keymanager/store/keys.py
gpg_keymanager/store/loader.py
gpg_keymanager/store/secret.py
gpg_keymanager-1.1.1.dist-info/LICENSE
gpg_keymanager-1.1.1.dist-info/WHEEL
gpg_keymanager-1.1.1.dist-info/entry_points.txt
gpg_keymanager-1.1.1.dist-info/METADATA
gpg_keymanager-1.1.1.dist-info/RECORD
