Metadata-Version: 2.1
Name: gpg-keymanager
Version: 1.1.1
Summary: gpg pass password store keyring management
Home-page: https://github.com/hile/gpg-keymanager
License: BSD
Author: Ilkka Tuohela
Author-email: hile@iki.fi
Requires-Python: >=3.9,<4.0
Classifier: Environment :: Console
Classifier: License :: OSI Approved :: BSD License
Classifier: License :: Other/Proprietary License
Classifier: Operating System :: MacOS
Classifier: Operating System :: POSIX
Classifier: Operating System :: Unix
Classifier: Programming Language :: Python :: 3
Classifier: Programming Language :: Python :: 3.9
Classifier: Programming Language :: Python :: 3.10
Classifier: Programming Language :: Python :: 3.11
Classifier: Programming Language :: Python :: 3.10
Classifier: Programming Language :: Python :: 3.11
Classifier: Programming Language :: Python :: 3.9
Classifier: Topic :: Security
Classifier: Topic :: Utilities
Requires-Dist: pathlib-tree (>=2,<3)
